README.rst
setup.cfg
setup.py
weaveq/__init__.py
weaveq/__main__.py
weaveq/application.py
weaveq/build_constants.py
weaveq/datasources.py
weaveq/parser.py
weaveq/query.py
weaveq/relations.py
weaveq/wqexception.py
weaveq.egg-info/PKG-INFO
weaveq.egg-info/SOURCES.txt
weaveq.egg-info/dependency_links.txt
weaveq.egg-info/entry_points.txt
weaveq.egg-info/not-zip-safe
weaveq.egg-info/requires.txt
weaveq.egg-info/top_level.txt