Metadata-Version: 1.1
Name: weaveq
Version: 0.1.4
Summary: Pivot and join across collections of data
Home-page: http://github.com/jamesmistry/weaveq
Author: James Mistry
Author-email: hello@jamesmistry.com
License: MIT
Download-URL: https://github.com/jamesmistry/weaveq/archive/0.1.0.tar.gz
Keywords: weaveq elasticsearch json csv pivot join correlate cross-reference
Platform: UNKNOWN
Classifier: License :: OSI Approved :: MIT License
Classifier: Development Status :: 5 - Production/Stable
Classifier: Environment :: Console
Classifier: Intended Audience :: Developers
Classifier: Intended Audience :: Science/Research
Classifier: Intended Audience :: System Administrators
Classifier: Natural Language :: English
Classifier: Operating System :: POSIX :: Linux
Classifier: Topic :: Scientific/Engineering :: Information Analysis
Classifier: Topic :: Software Development :: Libraries :: Python Modules
